omc/__init__.py
omc/main.py
omc/common/__init__.py
omc/common/common_completion.py
omc/common/formatter.py
omc/config/__init__.py
omc/config/settings.yaml
omc/core/__init__.py
omc/core/decorator.py
omc/core/resource.py
omc/core/terminal.py
omc/lib/__init__.py
omc/lib/_omc
omc/lib/omc-completion.sh
omc/resources/__init__.py
omc/resources/completion/__init__.py
omc/resources/completion/completion.py
omc/resources/config/__init__.py
omc/resources/config/config.py
omc/service/__init__.py
omc/service/omc_service.py
omc/utils/__init__.py
omc/utils/file_utils.py
omc/utils/object_utils.py
omc/webapp/__init__.py
omc/webapp/app.py
omc-0.2.5.dist-info/METADATA
omc-0.2.5.dist-info/WHEEL
omc-0.2.5.dist-info/entry_points.txt
omc-0.2.5.dist-info/top_level.txt
omc-0.2.5.dist-info/RECORD
