Metadata-Version: 2.1
Name: omc
Version: 0.2.5
Summary: oh my command
Home-page: https://github.com/linewx/omc
Author: Lu Ganlin
Author-email: linewx1981@gmail.com
License: MIT
Platform: UNKNOWN
Requires-Dist: requests (>=2.22.0)
Requires-Dist: dynaconf[all] (>=2.2.3)
Requires-Dist: pyfiglet (>=0.8.post1)
Requires-Dist: Click (>=7.0)
Requires-Dist: psutil (>=5.5)
Requires-Dist: pyyaml (>=5)
Requires-Dist: prettytable (>=0.7.2)
